multiviewstacking/__init__.py
multiviewstacking/data_utils.py
multiviewstacking/multi_view_stacking.py
multiviewstacking/data/HTAD Readme.txt
multiviewstacking/data/htad.csv
multiviewstacking-0.0.5.dist-info/LICENSE
multiviewstacking-0.0.5.dist-info/METADATA
multiviewstacking-0.0.5.dist-info/WHEEL
multiviewstacking-0.0.5.dist-info/top_level.txt
multiviewstacking-0.0.5.dist-info/RECORD
