Metadata-Version: 2.1
Name: multiviewstacking
Version: 0.0.5
Summary: Python implementation of the Multi-View Stacking algorithm.
Home-page: https://github.com/enriquegit/multiviewstacking
Author: Enrique Garcia-Ceja
Author-email: e.g.mx@ieee.org
License: MIT
Keywords: multi-view stacking,machine learning,classification,sensor fusion
Classifier: Programming Language :: Python :: 3
Classifier: License :: OSI Approved :: MIT License
Classifier: Operating System :: OS Independent
Requires-Python: >=3.8
License-File: LICENSE
Requires-Dist: pandas
Requires-Dist: numpy
Requires-Dist: scikit-learn (>=1.2.2)
